cdpchaosslack/__init__.py
cdpchaosslack/control.py
vztcdpchaos_slack-1.2.0.dist-info/LICENSE
vztcdpchaos_slack-1.2.0.dist-info/METADATA
vztcdpchaos_slack-1.2.0.dist-info/WHEEL
vztcdpchaos_slack-1.2.0.dist-info/top_level.txt
vztcdpchaos_slack-1.2.0.dist-info/RECORD
